{
  "name": "Dominic Foster",
  "age": 20,
  "address": {
    "street": "Zeziho Glen",
    "city": "Luhezar",
    "state": "TX",
    "zip": "75645"
  },
  "contact": {
    "phone": "(664) 686-6743",
    "servicePhone": "800969716"
  },
  "birthday": "1979-05-12T05:40:49.003Z",
  "ip": "194.240.11.233",
  "foo": "bar",
  "profile": {
    "about": "Gobdor fof derkuw uceh bepobi eci vachameg jezvalo co tun ekacir iwecaru fulowuru elo gomze. Sause ka sisce tizuwje ja uteato so kicudise barajej we fi sokjinam uhva dorinpud umva lasica epitiva. Nijza tiraoca cesukuet wolopva amu labahe iw joplu irabozij zi bog jehi be ajguckof bazol fe doftaipe. Et ceawe ajaba upubusved kuz idejo si di bogizano siglas sedis ka minuz.",
    "bio": "Osma hafcejju hi iwewet hucjed juwis siorha lapfo neznuusi ejafho las behmerdog. Ekduzaj oji puj tuj fu nec ohmin tu uk emzik dewvire ja dinli tuj canibot. Tiboruc woke amwe jefehvim rivjuile vuhic hizuuki acu tabvioso wauwufe ut no tu jot kizemam kavpup. Du sahja ma ekezolo bicbetos rieb ho puflizod hasjid ewani uwuatihe api runam vevrus ajvaope femroj. Ocaneso bo dahoce hodartiv roc nicebro junum havfiztir tac uhkidkos izsape ovpu ulcore coj ci gag giegowo lot. Ed filohjov gal ehubu visucazep pu gedakot ejirivhe cu otga evhiwan gichaja elab doewawu zalenfu hokusul. Ehu edonufhad wiwe sakew kop puravbeb lijziud norcu huhaha teginbit noh puwkote."
  },
  "apiKey": "bdca2699a96b0d2a2ebc49cd1e39478923b64b93b66270deb5e1332708ccf188",
  "currency": {
    "code": "UYU",
    "name": "Uruguay Peso"
  }
}