{
  "name": "Jonathan Armstrong",
  "age": 65,
  "address": {
    "street": "Gavfe Terrace",
    "city": "Jiwetrob",
    "state": "ND",
    "zip": "53432"
  },
  "contact": {
    "phone": "(558) 236-9412",
    "servicePhone": "800612736"
  },
  "birthday": "1978-08-15T14:15:53.400Z",
  "ip": "4.37.241.19",
  "foo": "bar",
  "profile": {
    "about": "Fomuh jadsivgo pujuce ahrizkid tuvomow hec afiepewab acdihguk ho kenevzuz ita pocuwno. Vic pikoz nocela omomusdas ma ni mufimepo ped cotekaav cedur do juk lejwe ez zi edpawad. Jerzud ut ir ze pefi kobijop kahfisboj tutocre ganhonwuk gulici niz rekiger. Ihi uza jatog ahoco une wogiiho ozato viwosium wop izmu cuob meuso erfo fafe.",
    "bio": "Paufaune az vajejawe jec fa ita kavefalin oznog ro gizacmuh wodlaepo kagimnu. Dekovib wef herir infif wa jur re furubjuf cewcij azomom peuj geckuilu. Netagu lanipehev efsafoc cup nujuh vowez jimed unfejep sipolti uvoif zead no puiteere bakdo zaazelif. Zu vollo ju jazwu pobhir geicde icrukmo al fom ivibi viavepek geka. Sibnadbaz bagciz icot bunwu gavemtib wubwe meed fabet ofasuw nean bubuniom bunrobwo mofwiiva. Icgege sip cigheos oweudaco tu kemtugud re zivlebtof derbiv zakumizaf fa dicog noget."
  },
  "apiKey": "c026e1ddd3bca9ad8bb3766b37d3ac562c438a90057d0ea3a64b58fbfe2a4bc7",
  "currency": {
    "code": "CVE",
    "name": "Cape Verde Escudo"
  }
}